classes/__init__.py
classes/argo.py
colchis-0.2.0.dist-info/METADATA
colchis-0.2.0.dist-info/WHEEL
colchis-0.2.0.dist-info/top_level.txt
colchis-0.2.0.dist-info/RECORD
