Metadata-Version: 2.1
Name: colchis
Version: 0.2.0
Summary: A package, implemented as a Class, to generalize JSON traversal and processing.
Author: Russell Bennett
Author-email: russell@beanbazaar.com
Project-URL: Homepage, https://github.com/Ipgnosis/colchis
Project-URL: Issues, https://github.com/Ipgnosis/colchis/issues
Classifier: Programming Language :: Python :: 3
Classifier: Operating System :: OS Independent
Requires-Python: >=3.8
